hi_baechu805/__init__.py
hi_baechu805/hello.py
hi_baechu805-0.8.0.dist-info/METADATA
hi_baechu805-0.8.0.dist-info/WHEEL
hi_baechu805-0.8.0.dist-info/entry_points.txt
hi_baechu805-0.8.0.dist-info/top_level.txt
hi_baechu805-0.8.0.dist-info/RECORD
