Metadata-Version: 2.1
Name: hi_baechu805
Version: 0.8.0
Summary: Default template for PDM package
Author-email: baechu805 <bjoo606@naver.com>
License: MIT
Requires-Python: ==3.12.*
